ceilosca/__init__.py
ceilosca/ceilometer/__init__.py
ceilosca/ceilometer/monasca_client.py
ceilosca/ceilometer/monasca_opts.py
ceilosca/ceilometer/opts.py
ceilosca/ceilometer/publisher/monasca.py
ceilosca/ceilometer/publisher/monasca_data_filter.py
ceilosca/ceilometer/tests/__init__.py
ceilosca/ceilometer/tests/unit/__init__.py
ceilosca/ceilometer/tests/unit/test_monascaclient.py
ceilosca/ceilometer/tests/unit/publisher/__init__.py
ceilosca/ceilometer/tests/unit/publisher/test_monasca_data_filter.py
ceilosca/ceilometer/tests/unit/publisher/test_monasca_publisher.py
monasca_ceilometer-1.10.0.dist-info/AUTHORS
monasca_ceilometer-1.10.0.dist-info/LICENSE
monasca_ceilometer-1.10.0.dist-info/METADATA
monasca_ceilometer-1.10.0.dist-info/WHEEL
monasca_ceilometer-1.10.0.dist-info/pbr.json
monasca_ceilometer-1.10.0.dist-info/top_level.txt
monasca_ceilometer-1.10.0.dist-info/RECORD
